dictionaries_addons_framework/__init__.py
dictionaries_addons_framework/__main__.py
dictionaries_addons_framework/addons.py
dictionaries_addons_framework-0.0.11.dist-info/METADATA
dictionaries_addons_framework-0.0.11.dist-info/WHEEL
dictionaries_addons_framework-0.0.11.dist-info/top_level.txt
dictionaries_addons_framework-0.0.11.dist-info/RECORD
